{
    "updated_at": "2026-05-04 19:17:30",
    "tracked_artists": [
        "ADORA",
        "ADYA",
        "AKMU",
        "ATARAYO",
        "Ai Tomioka",
        "Aimer",
        "Aooo",
        "Apink",
        "BABYMONSTER",
        "BADVILLAIN",
        "BAND-MAID",
        "BBGIRLS",
        "BIBI",
        "BLACKPINK",
        "BOL4",
        "BTS",
        "Baek A Yeon",
        "Billlie",
        "CLASS:y",
        "CSR",
        "Chilli Beans",
        "Choi Yoo jung",
        "Chung Ha",
        "Dreamcatcher",
        "EL7Z UP",
        "EVERGLOW",
        "Ellui",
        "Eunha",
        "FIFTY FIFTY",
        "Faulieu",
        "GFRIEND",
        "GOT the beat",
        "Geenius",
        "Gyubin",
        "H1-KEY",
        "HANA",
        "HUH YUNJIN",
        "Hayeon",
        "Hearts2Hearts",
        "Hebi",
        "HwaSa",
        "Hyoyeon",
        "ILLIT",
        "ILY:1",
        "ITZY",
        "IU",
        "IVE",
        "JIHYO",
        "JISOO",
        "JO YURI",
        "Jennie",
        "Jeong hyo bean",
        "Joy",
        "KARD",
        "KIMDOAH",
        "KISS OF LIFE",
        "Kang Hye Won",
        "Kassy",
        "Kep1er",
        "KiiiKiii",
        "Kim Mi Jeong",
        "Kim Sejeong",
        "Kwon Eun Bi",
        "KyoungSeo",
        "LATENCY",
        "LE SSERAFIM",
        "LEE CHAE YEON",
        "LEE HI",
        "LIGHTSUM",
        "LIMELIGHT",
        "LiSA",
        "Lim Kim",
        "Lisa",
        "MINAMI",
        "MRCH",
        "Majiko",
        "Mamamoo",
        "Minnie",
        "Miyeon",
        "Moonbyul",
        "NANA",
        "NAYEON",
        "NEK!",
        "NMIXX",
        "NewJeans",
        "OH MY GIRL",
        "Punch",
        "QWER",
        "RESCENE",
        "Red Velvet",
        "ReoNa",
        "Rosé",
        "Rothy",
        "Ryu Su Jeong",
        "SECRET NUMBER",
        "SEULGI",
        "SOOJIN",
        "STAYC",
        "SWAN",
        "Saebit",
        "Seo Dahyun",
        "SinB",
        "Solar",
        "Somi",
        "Soyeon",
        "Suzy",
        "T-ara",
        "TRI.BE",
        "TRiDENT",
        "TWICE",
        "TZUYU",
        "Taeyeon",
        "Umji",
        "VIVIZ",
        "WINTER",
        "WJSN",
        "Wendy",
        "Wheein",
        "Woo Yerin",
        "YENA",
        "YOASOBI",
        "Yein",
        "Yerin",
        "YooA",
        "Yorushika",
        "Younha",
        "Yuika",
        "Yuju",
        "Yunsae",
        "Yuqi",
        "ZUTOMAYO",
        "ado",
        "aespa",
        "aimyon",
        "chilldspot",
        "fromis_9",
        "i-dle",
        "izna",
        "lilli lilli",
        "siso",
        "tripleS",
        "tuki.",
        "woo!ah!",
        "yama",
        "ねぎ塩豚丼"
    ],
    "songs": [
        {
            "artist": "아이오아이 (I.O.I)",
            "title": "웃으며 안녕 (Recorded in 2016) (Prod.진영)",
            "image": "https://image.genie.co.kr/Y/IMAGE/IMG_ALBUM/087/566/103/87566103_1777432297657_1_140x140.JPG/dims/resize/Q_80,0",
            "link": "https://www.genie.co.kr/detail/songInfo?xgnm=114894511",
            "found_at": "2026-05-04 19:17",
            "is_tracked": false
        },
        {
            "artist": "BABYMONSTER",
            "title": "춤 (CHOOM)",
            "image": "https://image.genie.co.kr/Y/IMAGE/IMG_ALBUM/087/583/370/87583370_1777849894482_1_140x140.JPG/dims/resize/Q_80,0",
            "link": "https://www.genie.co.kr/detail/songInfo?xgnm=114950634",
            "found_at": "2026-05-04 19:17",
            "is_tracked": true
        },
        {
            "artist": "민기 (ATEEZ)",
            "title": "NOVA (Feat. 개코, Royal 44)",
            "image": "https://image.genie.co.kr/Y/IMAGE/IMG_ALBUM/087/529/660/87529660_1776750122174_1_140x140.JPG/dims/resize/Q_80,0",
            "link": "https://www.genie.co.kr/detail/songInfo?xgnm=114772544",
            "found_at": "2026-05-04 19:17",
            "is_tracked": false
        },
        {
            "artist": "CORTIS (코르티스)",
            "title": "GREENGREEN",
            "image": "https://image.genie.co.kr/Y/IMAGE/IMG_ALBUM/087/523/176/87523176_1777873825509_1_140x140.JPG/dims/resize/Q_80,0",
            "link": "https://www.genie.co.kr/detail/songInfo?xgnm=114752666",
            "found_at": "2026-05-04 19:17",
            "is_tracked": false
        },
        {
            "artist": "NAZE (네이즈)",
            "title": "NAZE",
            "image": "https://image.genie.co.kr/Y/IMAGE/IMG_ALBUM/087/561/567/87561567_1777367234171_1_140x140.JPG/dims/resize/Q_80,0",
            "link": "https://www.genie.co.kr/detail/songInfo?xgnm=114880328",
            "found_at": "2026-05-04 19:17",
            "is_tracked": false
        },
        {
            "artist": "매드 클라운 (Mad Clown)",
            "title": "수고했어 봄 (feat. siso(시소))",
            "image": "https://image.genie.co.kr/Y/IMAGE/IMG_ALBUM/087/571/851/87571851_1777530752288_1_140x140.JPG/dims/resize/Q_80,0",
            "link": "https://www.genie.co.kr/detail/songInfo?xgnm=114914623",
            "found_at": "2026-05-04 19:17",
            "is_tracked": false
        },
        {
            "artist": "1DB (원디비)",
            "title": "어느새",
            "image": "https://image.genie.co.kr/Y/IMAGE/IMG_ALBUM/087/568/619/87568619_1777466010384_1_140x140.JPG/dims/resize/Q_80,0",
            "link": "https://www.genie.co.kr/detail/songInfo?xgnm=114902991",
            "found_at": "2026-05-04 19:17",
            "is_tracked": false
        },
        {
            "artist": "가비엔제이 (Gavy NJ)",
            "title": "이별했대",
            "image": "https://image.genie.co.kr/Y/IMAGE/IMG_ALBUM/087/570/705/87570705_1777512727854_1_140x140.JPG/dims/resize/Q_80,0",
            "link": "https://www.genie.co.kr/detail/songInfo?xgnm=114910930",
            "found_at": "2026-05-04 19:17",
            "is_tracked": false
        },
        {
            "artist": "숙희",
            "title": "잘 지내고 있겠지",
            "image": "https://image.genie.co.kr/Y/IMAGE/IMG_ALBUM/087/566/158/87566158_1777535410165_1_140x140.JPG/dims/resize/Q_80,0",
            "link": "https://www.genie.co.kr/detail/songInfo?xgnm=114894734",
            "found_at": "2026-05-04 19:17",
            "is_tracked": false
        },
        {
            "artist": "정창룡",
            "title": "왜 너 때문에 눈물이 나는데",
            "image": "https://image.genie.co.kr/Y/IMAGE/IMG_ALBUM/087/567/749/87567749_1777455457797_1_140x140.JPG/dims/resize/Q_80,0",
            "link": "https://www.genie.co.kr/detail/songInfo?xgnm=114900286",
            "found_at": "2026-05-04 19:17",
            "is_tracked": false
        },
        {
            "artist": "장수빈",
            "title": "티키티키 (Tiki Tiki)",
            "image": "https://image.genie.co.kr/Y/IMAGE/IMG_ALBUM/087/540/240/87540240_1777453163384_1_140x140.JPG/dims/resize/Q_80,0",
            "link": "https://www.genie.co.kr/detail/songInfo?xgnm=114811229",
            "found_at": "2026-05-04 19:17",
            "is_tracked": false
        },
        {
            "artist": "won.e",
            "title": "WHY WHY WHY (웹툰 '정글쥬스' OST)",
            "image": "https://image.genie.co.kr/Y/IMAGE/IMG_ALBUM/087/565/596/87565596_1777425401116_1_140x140.JPG/dims/resize/Q_80,0",
            "link": "https://www.genie.co.kr/detail/songInfo?xgnm=114892347",
            "found_at": "2026-05-04 19:17",
            "is_tracked": false
        },
        {
            "artist": "한경일",
            "title": "너를 닮은 바람이 불어와",
            "image": "https://image.genie.co.kr/Y/IMAGE/IMG_ALBUM/087/570/700/87570700_1777512731830_1_140x140.JPG/dims/resize/Q_80,0",
            "link": "https://www.genie.co.kr/detail/songInfo?xgnm=114910922",
            "found_at": "2026-05-04 19:17",
            "is_tracked": false
        },
        {
            "artist": "J.cob (제이콥)",
            "title": "Trust It",
            "image": "https://image.genie.co.kr/Y/IMAGE/IMG_ALBUM/087/537/690/87537690_1777277931264_1_140x140.JPG/dims/resize/Q_80,0",
            "link": "https://www.genie.co.kr/detail/songInfo?xgnm=114799484",
            "found_at": "2026-05-04 19:17",
            "is_tracked": false
        },
        {
            "artist": "혜민",
            "title": "Oops",
            "image": "https://image.genie.co.kr/Y/IMAGE/IMG_ALBUM/087/555/509/87555509_1777541003829_1_140x140.JPG/dims/resize/Q_80,0",
            "link": "https://www.genie.co.kr/detail/songInfo?xgnm=114860873",
            "found_at": "2026-05-04 19:17",
            "is_tracked": false
        },
        {
            "artist": "노블(Novl)",
            "title": "Nvll",
            "image": "https://image.genie.co.kr/Y/IMAGE/IMG_ALBUM/087/545/131/87545131_1777013759572_1_140x140.JPG/dims/resize/Q_80,0",
            "link": "https://www.genie.co.kr/detail/songInfo?xgnm=114828383",
            "found_at": "2026-05-04 19:17",
            "is_tracked": false
        },
        {
            "artist": "DáFF",
            "title": "상처받을래",
            "image": "https://image.genie.co.kr/Y/IMAGE/IMG_ALBUM/087/555/441/87555441_1777275176811_1_140x140.JPG/dims/resize/Q_80,0",
            "link": "https://www.genie.co.kr/detail/songInfo?xgnm=114860667",
            "found_at": "2026-05-04 14:21",
            "is_tracked": false
        },
        {
            "artist": "Kohway & Nieah (니아)",
            "title": "AFRO TAPE 2",
            "image": "https://image.genie.co.kr/Y/IMAGE/IMG_ALBUM/087/554/716/87554716_1777535899891_1_140x140.JPG/dims/resize/Q_80,0",
            "link": "https://www.genie.co.kr/detail/songInfo?xgnm=114857373",
            "found_at": "2026-05-04 14:21",
            "is_tracked": false
        },
        {
            "artist": "Picturemegreen",
            "title": "Grace",
            "image": "https://image.genie.co.kr/Y/IMAGE/IMG_ALBUM/087/555/508/87555508_1777276346455_1_140x140.JPG/dims/resize/Q_80,0",
            "link": "https://www.genie.co.kr/detail/songInfo?xgnm=114860871",
            "found_at": "2026-05-04 14:21",
            "is_tracked": false
        },
        {
            "artist": "굿나잇스탠드",
            "title": "봄밤",
            "image": "https://image.genie.co.kr/Y/IMAGE/IMG_ALBUM/087/555/750/87555750_1777540995355_1_140x140.JPG/dims/resize/Q_80,0",
            "link": "https://www.genie.co.kr/detail/songInfo?xgnm=114861673",
            "found_at": "2026-05-04 14:21",
            "is_tracked": false
        },
        {
            "artist": "KOREANGROOVE",
            "title": "안녕",
            "image": "https://image.genie.co.kr/Y/IMAGE/IMG_ALBUM/087/555/181/87555181_1777270293364_1_140x140.JPG/dims/resize/Q_80,0",
            "link": "https://www.genie.co.kr/detail/songInfo?xgnm=114859432",
            "found_at": "2026-05-04 14:21",
            "is_tracked": false
        },
        {
            "artist": "문없는집",
            "title": "MIRAE COMPLEX Pt. 2",
            "image": "https://image.genie.co.kr/Y/IMAGE/IMG_ALBUM/087/555/121/87555121_1777453152803_1_140x140.JPG/dims/resize/Q_80,0",
            "link": "https://www.genie.co.kr/detail/songInfo?xgnm=114859126",
            "found_at": "2026-05-04 14:21",
            "is_tracked": false
        },
        {
            "artist": "손승연",
            "title": "1등들 Instrumental",
            "image": "https://image.genie.co.kr/Y/IMAGE/IMG_ALBUM/087/540/368/87540368_1776923793652_1_140x140.JPG/dims/resize/Q_80,0",
            "link": "https://www.genie.co.kr/detail/songInfo?xgnm=114811786",
            "found_at": "2026-05-04 14:21",
            "is_tracked": false
        },
        {
            "artist": "Otis Lim",
            "title": "Lemonade",
            "image": "https://image.genie.co.kr/Y/IMAGE/IMG_ALBUM/087/559/099/87559099_1777342591065_1_140x140.JPG/dims/resize/Q_80,0",
            "link": "https://www.genie.co.kr/detail/songInfo?xgnm=114873674",
            "found_at": "2026-05-04 14:21",
            "is_tracked": false
        },
        {
            "artist": "모닝커피 (Morning Coffee)",
            "title": "그리움 그대로",
            "image": "https://image.genie.co.kr/Y/IMAGE/IMG_ALBUM/087/536/642/87536642_1777515712167_1_140x140.JPG/dims/resize/Q_80,0",
            "link": "https://www.genie.co.kr/detail/songInfo?xgnm=114796092",
            "found_at": "2026-05-04 14:21",
            "is_tracked": false
        },
        {
            "artist": "타르트",
            "title": "그때는 몰랐어",
            "image": "https://image.genie.co.kr/Y/IMAGE/IMG_ALBUM/087/545/951/87545951_1777515847915_1_140x140.JPG/dims/resize/Q_80,0",
            "link": "https://www.genie.co.kr/detail/songInfo?xgnm=114831325",
            "found_at": "2026-05-04 14:21",
            "is_tracked": false
        },
        {
            "artist": "김손손",
            "title": "우리는 왜 살아가는 걸까",
            "image": "https://image.genie.co.kr/Y/IMAGE/IMG_ALBUM/087/561/621/87561621_1777367797477_1_140x140.JPG/dims/resize/Q_80,0",
            "link": "https://www.genie.co.kr/detail/songInfo?xgnm=114880438",
            "found_at": "2026-05-04 14:21",
            "is_tracked": false
        },
        {
            "artist": "시카 (CIKA)",
            "title": "SHAWTY",
            "image": "https://image.genie.co.kr/Y/IMAGE/IMG_ALBUM/087/562/974/87562974_1777455794721_1_140x140.JPG/dims/resize/Q_80,0",
            "link": "https://www.genie.co.kr/detail/songInfo?xgnm=114883622",
            "found_at": "2026-05-04 14:21",
            "is_tracked": false
        },
        {
            "artist": "아이런",
            "title": "Canopy Sky",
            "image": "https://image.genie.co.kr/Y/IMAGE/IMG_ALBUM/087/571/103/87571103_1777532788984_1_140x140.JPG/dims/resize/Q_80,0",
            "link": "https://www.genie.co.kr/detail/songInfo?xgnm=114912416",
            "found_at": "2026-05-04 14:21",
            "is_tracked": false
        },
        {
            "artist": "예다",
            "title": "사랑에 순서가 있는 거라면",
            "image": "https://image.genie.co.kr/Y/IMAGE/IMG_ALBUM/087/567/647/87567647_1777454523233_1_140x140.JPG/dims/resize/Q_80,0",
            "link": "https://www.genie.co.kr/detail/songInfo?xgnm=114900001",
            "found_at": "2026-05-04 14:21",
            "is_tracked": false
        },
        {
            "artist": "이시온",
            "title": "코스모스",
            "image": "https://image.genie.co.kr/Y/IMAGE/IMG_ALBUM/087/554/872/87554872_1777531703742_1_140x140.JPG/dims/resize/Q_80,0",
            "link": "https://www.genie.co.kr/detail/songInfo?xgnm=114857976",
            "found_at": "2026-05-04 14:21",
            "is_tracked": false
        },
        {
            "artist": "Happy Been & bxkwch & tawsogar",
            "title": "MONTAGEM SOJU",
            "image": "https://image.genie.co.kr/Y/IMAGE/IMG_ALBUM/087/536/481/87536481_1777515724677_1_140x140.JPG/dims/resize/Q_80,0",
            "link": "https://www.genie.co.kr/detail/songInfo?xgnm=114795451",
            "found_at": "2026-05-04 14:21",
            "is_tracked": false
        },
        {
            "artist": "경서 (Gyeongseo)",
            "title": "너와 함께 (With You)",
            "image": "https://image.genie.co.kr/Y/IMAGE/IMG_ALBUM/087/556/650/87556650_1777449134532_1_140x140.JPG/dims/resize/Q_80,0",
            "link": "https://www.genie.co.kr/detail/songInfo?xgnm=114864738",
            "found_at": "2026-05-04 14:21",
            "is_tracked": false
        },
        {
            "artist": "필헌",
            "title": "보내줄게",
            "image": "https://image.genie.co.kr/Y/IMAGE/IMG_ALBUM/087/561/100/87561100_1777362780078_1_140x140.JPG/dims/resize/Q_80,0",
            "link": "https://www.genie.co.kr/detail/songInfo?xgnm=114879199",
            "found_at": "2026-05-04 14:21",
            "is_tracked": false
        },
        {
            "artist": "홍지윤",
            "title": "내가 안아줄게요 (from 사랑을 처방해 드립니다 OST Part 8)",
            "image": "https://image.genie.co.kr/Y/IMAGE/IMG_ALBUM/087/568/847/87568847_1777479092016_1_140x140.JPG/dims/resize/Q_80,0",
            "link": "https://www.genie.co.kr/detail/songInfo?xgnm=114903816",
            "found_at": "2026-05-04 14:21",
            "is_tracked": false
        },
        {
            "artist": "최유리",
            "title": "모두가 자신의 무가치함과 싸우고 있다 OST Part.5",
            "image": "https://image.genie.co.kr/Y/IMAGE/IMG_ALBUM/087/567/486/87567486_1777452118375_1_140x140.JPG/dims/resize/Q_80,0",
            "link": "https://www.genie.co.kr/detail/songInfo?xgnm=114899202",
            "found_at": "2026-05-04 14:21",
            "is_tracked": false
        },
        {
            "artist": "이예준",
            "title": "같은 시간 속의 너",
            "image": "https://image.genie.co.kr/Y/IMAGE/IMG_ALBUM/087/566/579/87566579_1777438906238_1_140x140.JPG/dims/resize/Q_80,0",
            "link": "https://www.genie.co.kr/detail/songInfo?xgnm=114896185",
            "found_at": "2026-05-04 14:21",
            "is_tracked": false
        },
        {
            "artist": "Alexander Stewart",
            "title": "은밀한 감사 OST Part.2",
            "image": "https://image.genie.co.kr/Y/IMAGE/IMG_ALBUM/087/565/437/87565437_1777423953431_1_140x140.JPG/dims/resize/Q_80,0",
            "link": "https://www.genie.co.kr/detail/songInfo?xgnm=114891690",
            "found_at": "2026-05-04 14:21",
            "is_tracked": false
        },
        {
            "artist": "김장훈 & 하하",
            "title": "노래만 불렀지",
            "image": "https://image.genie.co.kr/Y/IMAGE/IMG_ALBUM/087/570/692/87570692_1777512704642_1_140x140.JPG/dims/resize/Q_80,0",
            "link": "https://www.genie.co.kr/detail/songInfo?xgnm=114910876",
            "found_at": "2026-05-04 14:21",
            "is_tracked": false
        },
        {
            "artist": "Alt (알트)",
            "title": "Weekend Sugar",
            "image": "https://image.genie.co.kr/Y/IMAGE/IMG_ALBUM/087/554/345/87554345_1777246903172_1_140x140.JPG/dims/resize/Q_80,0",
            "link": "https://www.genie.co.kr/detail/songInfo?xgnm=114856301",
            "found_at": "2026-05-04 14:21",
            "is_tracked": false
        },
        {
            "artist": "Kinn (킨)",
            "title": "이리 와",
            "image": "https://image.genie.co.kr/Y/IMAGE/IMG_ALBUM/087/558/713/87558713_1777436314954_1_140x140.JPG/dims/resize/Q_80,0",
            "link": "https://www.genie.co.kr/detail/songInfo?xgnm=114872123",
            "found_at": "2026-05-04 14:21",
            "is_tracked": false
        },
        {
            "artist": "윤성",
            "title": "나는 나를 잃지 않을게",
            "image": "https://image.genie.co.kr/Y/IMAGE/IMG_ALBUM/087/571/826/87571826_1777530446098_1_140x140.JPG/dims/resize/Q_80,0",
            "link": "https://www.genie.co.kr/detail/songInfo?xgnm=114914536",
            "found_at": "2026-05-04 14:21",
            "is_tracked": false
        },
        {
            "artist": "캄보 (KAMBO) & 키츠요지 (kitsyojii) & HD BL4CK",
            "title": "For The Hustlas 2026",
            "image": "https://image.genie.co.kr/Y/IMAGE/IMG_ALBUM/087/565/722/87565722_1777427516213_1_140x140.JPG/dims/resize/Q_80,0",
            "link": "https://www.genie.co.kr/detail/songInfo?xgnm=114893115",
            "found_at": "2026-05-04 14:21",
            "is_tracked": false
        },
        {
            "artist": "오연하",
            "title": "조금이라도 널 사랑할 때 헤어지자",
            "image": "https://image.genie.co.kr/Y/IMAGE/IMG_ALBUM/087/566/104/87566104_1777432352879_1_140x140.JPG/dims/resize/Q_80,0",
            "link": "https://www.genie.co.kr/detail/songInfo?xgnm=114894512",
            "found_at": "2026-05-04 14:21",
            "is_tracked": false
        },
        {
            "artist": "coa white",
            "title": "GT (feat. 0siggy)",
            "image": "https://image.genie.co.kr/Y/IMAGE/IMG_ALBUM/087/554/602/87554602_1777254098933_1_140x140.JPG/dims/resize/Q_80,0",
            "link": "https://www.genie.co.kr/detail/songInfo?xgnm=114856950",
            "found_at": "2026-05-04 14:21",
            "is_tracked": false
        },
        {
            "artist": "태리 (Terry)",
            "title": "장난이라고 말해줘",
            "image": "https://image.genie.co.kr/Y/IMAGE/IMG_ALBUM/087/554/772/87554772_1777536184186_1_140x140.JPG/dims/resize/Q_80,0",
            "link": "https://www.genie.co.kr/detail/songInfo?xgnm=114857601",
            "found_at": "2026-05-04 14:21",
            "is_tracked": false
        },
        {
            "artist": "아일릿(ILLIT)",
            "title": "MAMIHLAPINATAPAI",
            "image": "https://image.genie.co.kr/Y/IMAGE/IMG_ALBUM/087/567/808/87567808_1777456326075_1_140x140.JPG/dims/resize/Q_80,0",
            "link": "https://www.genie.co.kr/detail/songInfo?xgnm=114900451",
            "found_at": "2026-04-30 19:05",
            "is_tracked": true
        },
        {
            "artist": "유주 (YUJU)",
            "title": "첫사랑은 저주다",
            "image": "https://image.genie.co.kr/Y/IMAGE/IMG_ALBUM/087/529/962/87529962_1777373271477_1_140x140.JPG/dims/resize/Q_80,0",
            "link": "https://www.genie.co.kr/detail/songInfo?xgnm=114773530",
            "found_at": "2026-04-29 19:04",
            "is_tracked": true
        },
        {
            "artist": "QWER",
            "title": "4th Mini Album 'CEREMONY'",
            "image": "https://image.genie.co.kr/Y/IMAGE/IMG_ALBUM/087/540/872/87540872_1776931301386_1_140x140.JPG/dims/resize/Q_80,0",
            "link": "https://www.genie.co.kr/detail/songInfo?xgnm=114813326",
            "found_at": "2026-04-27 19:16",
            "is_tracked": true
        },
        {
            "artist": "태연 (TAEYEON)",
            "title": "모두가 자신의 무가치함과 싸우고 있다 OST Part.3",
            "image": "https://image.genie.co.kr/Y/IMAGE/IMG_ALBUM/087/545/008/87545008_1776999110650_1_140x140.JPG/dims/resize/Q_80,0",
            "link": "https://www.genie.co.kr/detail/songInfo?xgnm=114827854",
            "found_at": "2026-04-26 18:05",
            "is_tracked": true
        },
        {
            "artist": "LE SSERAFIM (르세라핌)",
            "title": "CELEBRATION",
            "image": "https://image.genie.co.kr/Y/IMAGE/IMG_ALBUM/087/544/291/87544291_1776989491847_1_140x140.JPG/dims/resize/Q_80,0",
            "link": "https://www.genie.co.kr/detail/songInfo?xgnm=114825112",
            "found_at": "2026-04-24 13:42",
            "is_tracked": true
        },
        {
            "artist": "리즈 (IVE)",
            "title": "첫 눈 그날처럼 (from 오늘도 매진했습니다 OST Part 1)",
            "image": "https://image.genie.co.kr/Y/IMAGE/IMG_ALBUM/087/528/728/87528728_1776735740033_1_140x140.JPG/dims/resize/Q_80,0",
            "link": "https://www.genie.co.kr/detail/songInfo?xgnm=114769655",
            "found_at": "2026-04-22 18:42",
            "is_tracked": true
        },
        {
            "artist": "Apink (에이핑크)",
            "title": "15th Season",
            "image": "https://image.genie.co.kr/Y/IMAGE/IMG_ALBUM/087/503/716/87503716_1776155508884_1_140x140.JPG/dims/resize/Q_80,0",
            "link": "https://www.genie.co.kr/detail/songInfo?xgnm=114691298",
            "found_at": "2026-04-19 18:00",
            "is_tracked": true
        },
        {
            "artist": "규빈 (GYUBIN)",
            "title": "Flower (한류 시작 20th 프로젝트 Part.7)",
            "image": "https://image.genie.co.kr/Y/IMAGE/IMG_ALBUM/087/512/330/87512330_1776327725619_1_140x140.JPG/dims/resize/Q_80,0",
            "link": "https://www.genie.co.kr/detail/songInfo?xgnm=114721072",
            "found_at": "2026-04-17 18:34",
            "is_tracked": true
        },
        {
            "artist": "아일릿 (ILLIT)",
            "title": "Bubee (Korean Ver.)",
            "image": "https://image.genie.co.kr/Y/IMAGE/IMG_ALBUM/087/498/169/87498169_1776045101740_1_140x140.JPG/dims/resize/Q_80,0",
            "link": "https://www.genie.co.kr/detail/songInfo?xgnm=114674921",
            "found_at": "2026-04-13 18:55",
            "is_tracked": true
        },
        {
            "artist": "미연 (MIYEON)",
            "title": "Bloom Again (Prod by Yoon Ilsang)",
            "image": "https://image.genie.co.kr/Y/IMAGE/IMG_ALBUM/087/487/929/87487929_1775784715132_1_140x140.JPG/dims/resize/Q_80,0",
            "link": "https://www.genie.co.kr/detail/songInfo?xgnm=114641445",
            "found_at": "2026-04-13 13:49",
            "is_tracked": true
        },
        {
            "artist": "KiiiKiii (키키)",
            "title": "21세기 대군부인 OST Part.2",
            "image": "https://image.genie.co.kr/Y/IMAGE/IMG_ALBUM/087/484/811/87484811_1775713596338_1_140x140.JPG/dims/resize/Q_80,0",
            "link": "https://www.genie.co.kr/detail/songInfo?xgnm=114630864",
            "found_at": "2026-04-11 17:56",
            "is_tracked": true
        },
        {
            "artist": "ZENE THE ZILLA (제네 더 질라) & Hash Swan & Nosun",
            "title": "AMBITION 4/10",
            "image": "https://image.genie.co.kr/Y/IMAGE/IMG_ALBUM/087/480/979/87480979_1775639490894_1_140x140.JPG/dims/resize/Q_80,0",
            "link": "https://www.genie.co.kr/detail/songInfo?xgnm=114617867",
            "found_at": "2026-04-10 18:16",
            "is_tracked": true
        },
        {
            "artist": "비비 (BIBI)",
            "title": "21세기 대군부인 OST Part.1",
            "image": "https://image.genie.co.kr/Y/IMAGE/IMG_ALBUM/087/484/806/87484806_1775713300842_1_140x140.JPG/dims/resize/Q_80,0",
            "link": "https://www.genie.co.kr/detail/songInfo?xgnm=114630844",
            "found_at": "2026-04-10 18:16",
            "is_tracked": true
        },
        {
            "artist": "화사 (HWASA)",
            "title": "So Cute",
            "image": "https://image.genie.co.kr/Y/IMAGE/IMG_ALBUM/087/481/426/87481426_1775649113805_1_140x140.JPG/dims/resize/Q_80,0",
            "link": "https://www.genie.co.kr/detail/songInfo?xgnm=114619216",
            "found_at": "2026-04-09 18:34",
            "is_tracked": true
        },
        {
            "artist": "Anyma & 리사 (LISA)",
            "title": "Bad Angel",
            "image": "https://image.genie.co.kr/Y/IMAGE/IMG_ALBUM/087/481/659/87481659_1775679147208_1_140x140.JPG/dims/resize/Q_80,0",
            "link": "https://www.genie.co.kr/detail/songInfo?xgnm=114620130",
            "found_at": "2026-04-09 13:21",
            "is_tracked": true
        },
        {
            "artist": "RESCENE (리센느)",
            "title": "Runaway",
            "image": "https://image.genie.co.kr/Y/IMAGE/IMG_ALBUM/087/458/490/87458490_1775115096303_1_140x140.JPG/dims/resize/Q_80,0",
            "link": "https://www.genie.co.kr/detail/songInfo?xgnm=114544535",
            "found_at": "2026-04-08 18:17",
            "is_tracked": true
        },
        {
            "artist": "AKMU (악뮤)",
            "title": "개화",
            "image": "https://image.genie.co.kr/Y/IMAGE/IMG_ALBUM/087/471/134/87471134_1775454694305_1_140x140.JPG/dims/resize/Q_80,0",
            "link": "https://www.genie.co.kr/detail/songInfo?xgnm=114585406",
            "found_at": "2026-04-07 18:16",
            "is_tracked": true
        },
        {
            "artist": "KISS OF LIFE",
            "title": "Who is she",
            "image": "https://image.genie.co.kr/Y/IMAGE/IMG_ALBUM/087/462/340/87462340_1775207815736_1_140x140.JPG/dims/resize/Q_80,0",
            "link": "https://www.genie.co.kr/detail/songInfo?xgnm=114558560",
            "found_at": "2026-04-06 18:19",
            "is_tracked": true
        },
        {
            "artist": "YEIN",
            "title": "Everything Is A Cycle",
            "image": "https://image.genie.co.kr/Y/IMAGE/IMG_ALBUM/087/427/734/87427734_1775098039997_1_140x140.JPG/dims/resize/Q_80,0",
            "link": "https://www.genie.co.kr/detail/songInfo?xgnm=114436601",
            "found_at": "2026-04-03 13:15",
            "is_tracked": true
        },
        {
            "artist": "케이시 (Kassy)",
            "title": "늦은 후회",
            "image": "https://image.genie.co.kr/Y/IMAGE/IMG_ALBUM/087/448/787/87448787_1774945389141_1_140x140.JPG/dims/resize/Q_80,0",
            "link": "https://www.genie.co.kr/detail/songInfo?xgnm=114510611",
            "found_at": "2026-04-01 18:15",
            "is_tracked": true
        },
        {
            "artist": "Kep1er (케플러)",
            "title": "CRACK CODE",
            "image": "https://image.genie.co.kr/Y/IMAGE/IMG_ALBUM/087/433/713/87433713_1774597914680_1_140x140.JPG/dims/resize/Q_80,0",
            "link": "https://www.genie.co.kr/detail/songInfo?xgnm=114458846",
            "found_at": "2026-03-31 18:13",
            "is_tracked": true
        },
        {
            "artist": "나나 (NANA)",
            "title": "클라이맥스 OST Part.3",
            "image": "https://image.genie.co.kr/Y/IMAGE/IMG_ALBUM/087/427/063/87427063_1774492334473_1_140x140.JPG/dims/resize/Q_80,0",
            "link": "https://www.genie.co.kr/detail/songInfo?xgnm=114434200",
            "found_at": "2026-03-31 18:13",
            "is_tracked": true
        },
        {
            "artist": "Hearts2Hearts (하츠투하츠) & Silly Silky (실리실키)",
            "title": "iScreaM Vol.39 : RUDE! Remixes",
            "image": "https://image.genie.co.kr/Y/IMAGE/IMG_ALBUM/087/428/518/87428518_1774512691192_1_140x140.JPG/dims/resize/Q_80,0",
            "link": "https://www.genie.co.kr/detail/songInfo?xgnm=114439186",
            "found_at": "2026-03-27 18:06",
            "is_tracked": true
        },
        {
            "artist": "유나 (ITZY)",
            "title": "Ice Cream (Remixes)",
            "image": "https://image.genie.co.kr/Y/IMAGE/IMG_ALBUM/087/422/650/87422650_1774407432776_1_140x140.JPG/dims/resize/Q_80,0",
            "link": "https://www.genie.co.kr/detail/songInfo?xgnm=114418481",
            "found_at": "2026-03-27 13:18",
            "is_tracked": true
        },
        {
            "artist": "CSR (첫사랑)",
            "title": "［ASTROCHILD IN THE LONELY PLANET］ CSR(첫사랑) - 숨길 수 없는 맘인걸",
            "image": "https://image.genie.co.kr/Y/IMAGE/IMG_ALBUM/087/423/932/87423932_1774424190691_1_140x140.JPG/dims/resize/Q_80,0",
            "link": "https://www.genie.co.kr/detail/songInfo?xgnm=114423829",
            "found_at": "2026-03-26 18:11",
            "is_tracked": true
        },
        {
            "artist": "FIFTY FIFTY",
            "title": "Wish You Were Here",
            "image": "https://image.genie.co.kr/Y/IMAGE/IMG_ALBUM/087/390/756/87390756_1773738707708_1_140x140.JPG/dims/resize/Q_80,0",
            "link": "https://www.genie.co.kr/detail/songInfo?xgnm=114310731",
            "found_at": "2026-03-24 13:03",
            "is_tracked": true
        },
        {
            "artist": "유나 (ITZY)",
            "title": "Ice Cream",
            "image": "https://image.genie.co.kr/Y/IMAGE/IMG_ALBUM/087/405/207/87405207_1773984090987_1_140x140.JPG/dims/resize/Q_80,0",
            "link": "https://www.genie.co.kr/detail/songInfo?xgnm=114360759",
            "found_at": "2026-03-23 18:13",
            "is_tracked": true
        },
        {
            "artist": "Super Joy Club",
            "title": "Fall In Peace",
            "image": "https://image.genie.co.kr/Y/IMAGE/IMG_ALBUM/087/400/852/87400852_1773907919286_1_140x140.JPG/dims/resize/Q_80,0",
            "link": "https://www.genie.co.kr/detail/songInfo?xgnm=114347960",
            "found_at": "2026-03-23 13:14",
            "is_tracked": true
        },
        {
            "artist": "LATENCY (레이턴시)",
            "title": "LATE O' CLOCK",
            "image": "https://image.genie.co.kr/Y/IMAGE/IMG_ALBUM/087/390/691/87390691_1773736899297_1_140x140.JPG/dims/resize/Q_80,0",
            "link": "https://www.genie.co.kr/detail/songInfo?xgnm=114310472",
            "found_at": "2026-03-18 18:11",
            "is_tracked": true
        },
        {
            "artist": "정소연 (Jung Soyeon)",
            "title": "그대에게 불러봐요",
            "image": "https://image.genie.co.kr/Y/IMAGE/IMG_ALBUM/087/390/686/87390686_1773736322042_1_140x140.JPG/dims/resize/Q_80,0",
            "link": "https://www.genie.co.kr/detail/songInfo?xgnm=114310459",
            "found_at": "2026-03-18 18:11",
            "is_tracked": true
        },
        {
            "artist": "YENA (최예나)",
            "title": "캐치 캐치 (Sped Up)",
            "image": "https://image.genie.co.kr/Y/IMAGE/IMG_ALBUM/087/384/854/87384854_1773628296803_1_140x140.JPG/dims/resize/Q_80,0",
            "link": "https://www.genie.co.kr/detail/songInfo?xgnm=114293662",
            "found_at": "2026-03-17 18:08",
            "is_tracked": true
        },
        {
            "artist": "민니 (MINNIE)",
            "title": "세이렌 OST Part.3",
            "image": "https://image.genie.co.kr/Y/IMAGE/IMG_ALBUM/087/375/503/87375503_1773362501920_1_140x140.JPG/dims/resize/Q_80,0",
            "link": "https://www.genie.co.kr/detail/songInfo?xgnm=114265418",
            "found_at": "2026-03-16 18:14",
            "is_tracked": true
        },
        {
            "artist": "siso (시소)",
            "title": "1972",
            "image": "https://image.genie.co.kr/Y/IMAGE/IMG_ALBUM/087/372/024/87372024_1773294127640_1_140x140.JPG/dims/resize/Q_80,0",
            "link": "https://www.genie.co.kr/detail/songInfo?xgnm=114254812",
            "found_at": "2026-03-15 17:49",
            "is_tracked": true
        },
        {
            "artist": "Galantis & RESCENE (리센느)",
            "title": "Busy Boy (Galantis Remix)",
            "image": "https://image.genie.co.kr/Y/IMAGE/IMG_ALBUM/087/344/772/87344772_1773106020244_1_140x140.JPG/dims/resize/Q_80,0",
            "link": "https://www.genie.co.kr/detail/songInfo?xgnm=114172427",
            "found_at": "2026-03-12 12:57",
            "is_tracked": true
        },
        {
            "artist": "YENA (최예나)",
            "title": "LOVE CATCHER",
            "image": "https://image.genie.co.kr/Y/IMAGE/IMG_ALBUM/087/346/195/87346195_1772787097585_1_140x140.JPG/dims/resize/Q_80,0",
            "link": "https://www.genie.co.kr/detail/songInfo?xgnm=114176738",
            "found_at": "2026-03-11 17:59",
            "is_tracked": true
        },
        {
            "artist": "던말릭 (DON MALIK) & Hash Swan",
            "title": "AMBITION 3/10",
            "image": "https://image.genie.co.kr/Y/IMAGE/IMG_ALBUM/087/356/276/87356276_1773035275741_1_140x140.JPG/dims/resize/Q_80,0",
            "link": "https://www.genie.co.kr/detail/songInfo?xgnm=114205707",
            "found_at": "2026-03-10 18:00",
            "is_tracked": true
        },
        {
            "artist": "윤하 (YOUNHA)",
            "title": "윤하 리메이크 앨범 '써브캐릭터 원'",
            "image": "https://image.genie.co.kr/Y/IMAGE/IMG_ALBUM/087/207/064/87207064_1772788347139_1_140x140.JPG/dims/resize/Q_80,0",
            "link": "https://www.genie.co.kr/detail/songInfo?xgnm=114176710",
            "found_at": "2026-03-09 18:06",
            "is_tracked": true
        },
        {
            "artist": "윤마치 (MRCH)",
            "title": "미혼남녀의 효율적 만남 OST Part.2",
            "image": "https://image.genie.co.kr/Y/IMAGE/IMG_ALBUM/087/338/344/87338344_1772705467033_1_140x140.JPG/dims/resize/Q_80,0",
            "link": "https://www.genie.co.kr/detail/songInfo?xgnm=114150525",
            "found_at": "2026-03-08 17:44",
            "is_tracked": true
        },
        {
            "artist": "로시 (Rothy)",
            "title": "샤이닝 OST Part.2",
            "image": "https://image.genie.co.kr/Y/IMAGE/IMG_ALBUM/087/344/497/87344497_1772765813870_1_140x140.JPG/dims/resize/Q_80,0",
            "link": "https://www.genie.co.kr/detail/songInfo?xgnm=114171769",
            "found_at": "2026-03-07 17:42",
            "is_tracked": true
        },
        {
            "artist": "YEIN",
            "title": "wawawa",
            "image": "https://image.genie.co.kr/Y/IMAGE/IMG_ALBUM/087/314/349/87314349_1772676874180_1_140x140.JPG/dims/resize/Q_80,0",
            "link": "https://www.genie.co.kr/detail/songInfo?xgnm=114065678",
            "found_at": "2026-03-07 12:39",
            "is_tracked": true
        },
        {
            "artist": "제니 (JENNIE)",
            "title": "Ruby (The Complete Collection)",
            "image": "https://image.genie.co.kr/Y/IMAGE/IMG_ALBUM/087/344/038/87344038_1772761632514_1_140x140.JPG/dims/resize/Q_80,0",
            "link": "https://www.genie.co.kr/detail/songInfo?xgnm=114170338",
            "found_at": "2026-03-06 17:56",
            "is_tracked": true
        },
        {
            "artist": "H1-KEY (하이키)",
            "title": "LOVECHAPTER",
            "image": "https://image.genie.co.kr/Y/IMAGE/IMG_ALBUM/087/336/847/87336847_1772593892162_1_140x140.JPG/dims/resize/Q_80,0",
            "link": "https://www.genie.co.kr/detail/songInfo?xgnm=114144781",
            "found_at": "2026-03-05 18:01",
            "is_tracked": true
        },
        {
            "artist": "EVERGLOW (에버글로우)",
            "title": "CODE",
            "image": "https://image.genie.co.kr/Y/IMAGE/IMG_ALBUM/087/314/363/87314363_1772170751387_1_140x140.JPG/dims/resize/Q_80,0",
            "link": "https://www.genie.co.kr/detail/songInfo?xgnm=114065811",
            "found_at": "2026-03-03 18:00",
            "is_tracked": true
        },
        {
            "artist": "BLACKPINK",
            "title": "DEADLINE",
            "image": "https://image.genie.co.kr/Y/IMAGE/IMG_ALBUM/087/316/685/87316685_1772156918165_1_140x140.JPG/dims/resize/Q_80,0",
            "link": "https://www.genie.co.kr/detail/songInfo?xgnm=114076239",
            "found_at": "2026-02-27 17:59",
            "is_tracked": true
        },
        {
            "artist": "웬디 (WENDY) & Alec Benjamin",
            "title": "EMOTIONS",
            "image": "https://image.genie.co.kr/Y/IMAGE/IMG_ALBUM/087/163/750/87163750_1772167605283_1_140x140.JPG/dims/resize/Q_80,0",
            "link": "https://www.genie.co.kr/detail/songInfo?xgnm=113509378",
            "found_at": "2026-02-27 17:59",
            "is_tracked": true
        },
        {
            "artist": "aespa & Anderson .Paak",
            "title": "Keychain (FROM THE FILM K-POPS!)",
            "image": "https://image.genie.co.kr/Y/IMAGE/IMG_ALBUM/087/311/152/87311152_1772172990959_1_140x140.JPG/dims/resize/Q_80,0",
            "link": "https://www.genie.co.kr/detail/songInfo?xgnm=114051904",
            "found_at": "2026-02-27 17:59",
            "is_tracked": true
        },
        {
            "artist": "RESCENE (리센느)",
            "title": "［RESCENE X ???］",
            "image": "https://image.genie.co.kr/Y/IMAGE/IMG_ALBUM/087/301/643/87301643_1772154691174_1_140x140.JPG/dims/resize/Q_80,0",
            "link": "https://www.genie.co.kr/detail/songInfo?xgnm=114016866",
            "found_at": "2026-02-27 17:59",
            "is_tracked": true
        },
        {
            "artist": "윤새 (Yunsae)",
            "title": "Forevermore",
            "image": "https://image.genie.co.kr/Y/IMAGE/IMG_ALBUM/087/272/111/87272111_1771127798878_1_140x140.JPG/dims/resize/Q_80,0",
            "link": "https://www.genie.co.kr/detail/songInfo?xgnm=113919512",
            "found_at": "2026-02-27 17:59",
            "is_tracked": true
        },
        {
            "artist": "NMIXX",
            "title": "TIC TIC (feat. Pabllo Vittar)",
            "image": "https://image.genie.co.kr/Y/IMAGE/IMG_ALBUM/087/309/360/87309360_1771985276037_1_140x140.JPG/dims/resize/Q_80,0",
            "link": "https://www.genie.co.kr/detail/songInfo?xgnm=114044740",
            "found_at": "2026-02-26 13:01",
            "is_tracked": true
        },
        {
            "artist": "박재정 & 설윤 (NMIXX)",
            "title": "지금 이대로만",
            "image": "https://image.genie.co.kr/Y/IMAGE/IMG_ALBUM/087/305/626/87305626_1771918545771_1_140x140.JPG/dims/resize/Q_80,0",
            "link": "https://www.genie.co.kr/detail/songInfo?xgnm=114031943",
            "found_at": "2026-02-25 18:10",
            "is_tracked": true
        },
        {
            "artist": "Kep1er (케플러)",
            "title": "I Stay (From '너자 2')",
            "image": "https://image.genie.co.kr/Y/IMAGE/IMG_ALBUM/087/302/277/87302277_1771920820823_1_140x140.JPG/dims/resize/Q_80,0",
            "link": "https://www.genie.co.kr/detail/songInfo?xgnm=114019342",
            "found_at": "2026-02-25 13:03",
            "is_tracked": true
        },
        {
            "artist": "IVE (아이브)",
            "title": "REVIVE＋",
            "image": "https://image.genie.co.kr/Y/IMAGE/IMG_ALBUM/087/233/225/87233225_1771579384466_1_140x140.JPG/dims/resize/Q_80,0",
            "link": "https://www.genie.co.kr/detail/songInfo?xgnm=113986758",
            "found_at": "2026-02-23 18:11",
            "is_tracked": true
        },
        {
            "artist": "웬디 (WENDY)",
            "title": "오늘부터 인간입니다만 OST Special All Track",
            "image": "https://image.genie.co.kr/Y/IMAGE/IMG_ALBUM/087/255/211/87255211_1770787984579_1_140x140.JPG/dims/resize/Q_80,0",
            "link": "https://www.genie.co.kr/detail/songInfo?xgnm=113867357",
            "found_at": "2026-02-21 12:46",
            "is_tracked": true
        },
        {
            "artist": "Hearts2Hearts (하츠투하츠)",
            "title": "RUDE!",
            "image": "https://image.genie.co.kr/Y/IMAGE/IMG_ALBUM/087/287/901/87287901_1771485100205_1_140x140.JPG/dims/resize/Q_80,0",
            "link": "https://www.genie.co.kr/detail/songInfo?xgnm=113970278",
            "found_at": "2026-02-20 17:57",
            "is_tracked": true
        },
        {
            "artist": "Super Joy Club",
            "title": "어떻게 평화할까?",
            "image": "https://image.genie.co.kr/Y/IMAGE/IMG_ALBUM/087/250/002/87250002_1770702695103_1_140x140.JPG/dims/resize/Q_80,0",
            "link": "https://www.genie.co.kr/detail/songInfo?xgnm=113849465",
            "found_at": "2026-02-18 18:05",
            "is_tracked": true
        },
        {
            "artist": "엘루이 (Ellui)",
            "title": "아너 : 그녀들의 법정 OST Part.3",
            "image": "https://image.genie.co.kr/Y/IMAGE/IMG_ALBUM/087/248/937/87248937_1770684774802_1_140x140.JPG/dims/resize/Q_80,0",
            "link": "https://www.genie.co.kr/detail/songInfo?xgnm=113845703",
            "found_at": "2026-02-16 13:10",
            "is_tracked": true
        },
        {
            "artist": "YEIN",
            "title": "Trouble",
            "image": "https://image.genie.co.kr/Y/IMAGE/IMG_ALBUM/087/206/863/87206863_1770945585300_1_140x140.JPG/dims/resize/Q_80,0",
            "link": "https://www.genie.co.kr/detail/songInfo?xgnm=113694799",
            "found_at": "2026-02-14 12:51",
            "is_tracked": true
        },
        {
            "artist": "로시 (Rothy) & 하은 (포맨)",
            "title": "우주를 줄게 OST Part.2",
            "image": "https://image.genie.co.kr/Y/IMAGE/IMG_ALBUM/087/249/106/87249106_1770718000399_1_140x140.JPG/dims/resize/Q_80,0",
            "link": "https://www.genie.co.kr/detail/songInfo?xgnm=113846258",
            "found_at": "2026-02-12 18:07",
            "is_tracked": true
        },
        {
            "artist": "벨 (KISS OF LIFE)",
            "title": "웹툰 '재혼 황후' OST Part. 1",
            "image": "https://image.genie.co.kr/Y/IMAGE/IMG_ALBUM/087/206/771/87206771_1770706831793_1_140x140.JPG/dims/resize/Q_80,0",
            "link": "https://www.genie.co.kr/detail/songInfo?xgnm=113694441",
            "found_at": "2026-02-11 18:09",
            "is_tracked": true
        },
        {
            "artist": "IVE (아이브)",
            "title": "REVIVE＋",
            "image": "https://image.genie.co.kr/Y/IMAGE/IMG_ALBUM/087/233/225/87233225_1770354427282_1_140x140.JPG/dims/resize/Q_80,0",
            "link": "https://www.genie.co.kr/detail/songInfo?xgnm=113791695",
            "found_at": "2026-02-09 18:16",
            "is_tracked": true
        },
        {
            "artist": "웬디 (WENDY)",
            "title": "오늘부터 인간입니다만 OST Part.5",
            "image": "https://image.genie.co.kr/Y/IMAGE/IMG_ALBUM/087/215/054/87215054_1770000527961_1_140x140.JPG/dims/resize/Q_80,0",
            "link": "https://www.genie.co.kr/detail/songInfo?xgnm=113725507",
            "found_at": "2026-02-07 17:45",
            "is_tracked": true
        },
        {
            "artist": "케이시 (Kassy)",
            "title": "언더커버 미쓰홍 OST Part.5",
            "image": "https://image.genie.co.kr/Y/IMAGE/IMG_ALBUM/087/233/000/87233000_1770347860028_1_140x140.JPG/dims/resize/Q_80,0",
            "link": "https://www.genie.co.kr/detail/songInfo?xgnm=113790481",
            "found_at": "2026-02-07 17:45",
            "is_tracked": true
        },
        {
            "artist": "Tame Impala & 제니 (JENNIE)",
            "title": "Dracula (Remix)",
            "image": "https://image.genie.co.kr/Y/IMAGE/IMG_ALBUM/087/218/983/87218983_1770084694179_1_140x140.JPG/dims/resize/Q_80,0",
            "link": "https://www.genie.co.kr/detail/songInfo?xgnm=113739898",
            "found_at": "2026-02-06 12:57",
            "is_tracked": true
        }
    ]
}